{
  "annotations": {
    "list": [
      {
        "builtIn": 1,
        "datasource": {
          "type": "grafana",
          "uid": "-- Grafana --"
        },
        "enable": true,
        "hide": true,
        "iconColor": "rgba(0, 211, 255, 1)",
        "name": "Annotations & Alerts",
        "type": "dashboard"
      }
    ]
  },
  "editable": true,
  "fiscalYearStartMonth": 0,
  "graphTooltip": 0,
  "id": 271557,
  "links": [],
  "liveNow": false,
  "panels": [
    {
      "alert": {
        "alertRuleTags": {},
        "conditions": [
          {
            "evaluator": {
              "params": [
                50
              ],
              "type": "gt"
            },
            "operator": {
              "type": "and"
            },
            "query": {
              "params": [
                "B",
                "1h",
                "now"
              ]
            },
            "reducer": {
              "params": [],
              "type": "last"
            },
            "type": "query"
          }
        ],
        "executionErrorState": "alerting",
        "for": "0",
        "frequency": "1h",
        "handler": 1,
        "message": "",
        "name": "cdc_flume",
        "noDataState": "ok",
        "notifications": [
          {
            "uid": "f20a9478-e17e-4cca-81a3-1bce008ccc8b"
          }
        ]
      },
      "datasource": {
        "type": "loki",
        "uid": "onprem-loki-prd-1"
      },
      "fieldConfig": {
        "defaults": {
          "color": {
            "mode": "palette-classic"
          },
          "custom": {
            "axisCenteredZero": false,
            "axisColorMode": "text",
            "axisLabel": "",
            "axisPlacement": "auto",
            "barAlignment": 0,
            "drawStyle": "line",
            "fillOpacity": 0,
            "gradientMode": "none",
            "hideFrom": {
              "legend": false,
              "tooltip": false,
              "viz": false
            },
            "lineInterpolation": "linear",
            "lineWidth": 1,
            "pointSize": 5,
            "scaleDistribution": {
              "type": "linear"
            },
            "showPoints": "auto",
            "spanNulls": false,
            "stacking": {
              "group": "A",
              "mode": "none"
            },
            "thresholdsStyle": {
              "mode": "off"
            }
          },
          "mappings": [],
          "thresholds": {
            "mode": "absolute",
            "steps": [
              {
                "color": "green",
                "value": null
              },
              {
                "color": "red",
                "value": 80
              }
            ]
          }
        },
        "overrides": []
      },
      "gridPos": {
        "h": 8,
        "w": 12,
        "x": 0,
        "y": 0
      },
      "id": 2,
      "options": {
        "legend": {
          "calcs": [],
          "displayMode": "list",
          "placement": "bottom",
          "showLegend": true
        },
        "tooltip": {
          "mode": "single",
          "sort": "none"
        }
      },
      "targets": [
        {
          "datasource": {
            "type": "loki",
            "uid": "onprem-loki-prd-1"
          },
          "editorMode": "code",
          "expr": "sum(count(rate({containerId=\"cdc_flume\"} |= `error` [$__interval])))",
          "hide": true,
          "queryType": "range",
          "refId": "A"
        },
        {
          "datasource": {
            "type": "loki",
            "uid": "onprem-loki-prd-1"
          },
          "editorMode": "code",
          "expr": "count(rate({containerId=\"cdc_flume\"} |= \"error\" [1h])) by (containerId, errorType)",
          "hide": false,
          "queryType": "range",
          "refId": "B"
        }
      ],
      "thresholds": [
        {
          "colorMode": "critical",
          "op": "gt",
          "value": 50,
          "visible": true
        }
      ],
      "title": "CDC Flume",
      "type": "timeseries"
    },
    {
      "datasource": {
        "type": "loki",
        "uid": "onprem-loki-prd-1"
      },
      "gridPos": {
        "h": 8,
        "w": 12,
        "x": 12,
        "y": 0
      },
      "id": 1,
      "options": {
        "dedupStrategy": "none",
        "enableLogDetails": true,
        "prettifyLogMessage": false,
        "showCommonLabels": false,
        "showLabels": false,
        "showTime": false,
        "sortOrder": "Descending",
        "wrapLogMessage": false
      },
      "targets": [
        {
          "datasource": {
            "type": "loki",
            "uid": "onprem-loki-prd-1"
          },
          "editorMode": "code",
          "expr": "{containerId=\"cdc_flume\"} |= `error`",
          "key": "Q-c5a8776e-8c93-448b-aa5c-f5611a376d54-0",
          "queryType": "range",
          "refId": "A"
        }
      ],
      "title": "CDC Flume Logs",
      "type": "logs"
    },
    {
      "alert": {
        "alertRuleTags": {},
        "conditions": [
          {
            "evaluator": {
              "params": [
                50
              ],
              "type": "gt"
            },
            "operator": {
              "type": "and"
            },
            "query": {
              "params": [
                "B",
                "1h",
                "now"
              ]
            },
            "reducer": {
              "params": [],
              "type": "last"
            },
            "type": "query"
          }
        ],
        "executionErrorState": "alerting",
        "for": "0",
        "frequency": "1h",
        "handler": 1,
        "message": "",
        "name": "CDC Grpc Out Logs alert",
        "noDataState": "ok",
        "notifications": [
          {
            "uid": "f20a9478-e17e-4cca-81a3-1bce008ccc8b"
          }
        ]
      },
      "datasource": {
        "type": "loki",
        "uid": "onprem-loki-prd-1"
      },
      "fieldConfig": {
        "defaults": {
          "color": {
            "mode": "palette-classic"
          },
          "custom": {
            "axisCenteredZero": false,
            "axisColorMode": "text",
            "axisLabel": "",
            "axisPlacement": "auto",
            "barAlignment": 0,
            "drawStyle": "line",
            "fillOpacity": 0,
            "gradientMode": "none",
            "hideFrom": {
              "legend": false,
              "tooltip": false,
              "viz": false
            },
            "lineInterpolation": "linear",
            "lineWidth": 1,
            "pointSize": 5,
            "scaleDistribution": {
              "type": "linear"
            },
            "showPoints": "auto",
            "spanNulls": false,
            "stacking": {
              "group": "A",
              "mode": "none"
            },
            "thresholdsStyle": {
              "mode": "off"
            }
          },
          "mappings": [],
          "thresholds": {
            "mode": "absolute",
            "steps": [
              {
                "color": "green",
                "value": null
              },
              {
                "color": "red",
                "value": 80
              }
            ]
          }
        },
        "overrides": []
      },
      "gridPos": {
        "h": 8,
        "w": 12,
        "x": 0,
        "y": 8
      },
      "id": 5,
      "options": {
        "legend": {
          "calcs": [],
          "displayMode": "list",
          "placement": "bottom",
          "showLegend": true
        },
        "tooltip": {
          "mode": "single",
          "sort": "none"
        }
      },
      "targets": [
        {
          "datasource": {
            "type": "loki",
            "uid": "onprem-loki-prd-1"
          },
          "editorMode": "builder",
          "expr": "sum(count(rate({containerId=\"cdc_grpc_out\"} |= `error` [$__interval])))",
          "hide": true,
          "queryType": "range",
          "refId": "A"
        },
        {
          "datasource": {
            "type": "loki",
            "uid": "onprem-loki-prd-1"
          },
          "editorMode": "code",
          "expr": "count(rate({containerId=\"cdc_grpc_out\"} |= \"error\" [1h])) by (containerId, errorType)",
          "hide": false,
          "queryType": "range",
          "refId": "B"
        }
      ],
      "thresholds": [
        {
          "colorMode": "critical",
          "op": "gt",
          "value": 50,
          "visible": true
        }
      ],
      "title": "CDC Grpc Out",
      "type": "timeseries"
    },
    {
      "datasource": {
        "type": "loki",
        "uid": "onprem-loki-prd-1"
      },
      "gridPos": {
        "h": 8,
        "w": 12,
        "x": 12,
        "y": 8
      },
      "id": 6,
      "options": {
        "dedupStrategy": "none",
        "enableLogDetails": true,
        "prettifyLogMessage": false,
        "showCommonLabels": false,
        "showLabels": false,
        "showTime": false,
        "sortOrder": "Descending",
        "wrapLogMessage": false
      },
      "targets": [
        {
          "datasource": {
            "type": "loki",
            "uid": "onprem-loki-prd-1"
          },
          "editorMode": "builder",
          "expr": "{containerId=\"cdc_grpc_out\"} |= `error`",
          "key": "Q-c5a8776e-8c93-448b-aa5c-f5611a376d54-0",
          "queryType": "range",
          "refId": "A"
        }
      ],
      "title": "CDC Grpc Out Logs",
      "type": "logs"
    },
    {
      "alert": {
        "alertRuleTags": {},
        "conditions": [
          {
            "evaluator": {
              "params": [
                50
              ],
              "type": "gt"
            },
            "operator": {
              "type": "and"
            },
            "query": {
              "params": [
                "B",
                "1h",
                "now"
              ]
            },
            "reducer": {
              "params": [],
              "type": "last"
            },
            "type": "query"
          }
        ],
        "executionErrorState": "alerting",
        "for": "0",
        "frequency": "1h",
        "handler": 1,
        "message": "",
        "name": "CDC Grpc In Logs alert",
        "noDataState": "ok",
        "notifications": [
          {
            "uid": "f20a9478-e17e-4cca-81a3-1bce008ccc8b"
          }
        ]
      },
      "datasource": {
        "type": "loki",
        "uid": "onprem-loki-prd-1"
      },
      "fieldConfig": {
        "defaults": {
          "color": {
            "mode": "palette-classic"
          },
          "custom": {
            "axisCenteredZero": false,
            "axisColorMode": "text",
            "axisLabel": "",
            "axisPlacement": "auto",
            "barAlignment": 0,
            "drawStyle": "line",
            "fillOpacity": 0,
            "gradientMode": "none",
            "hideFrom": {
              "legend": false,
              "tooltip": false,
              "viz": false
            },
            "lineInterpolation": "linear",
            "lineWidth": 1,
            "pointSize": 5,
            "scaleDistribution": {
              "type": "linear"
            },
            "showPoints": "auto",
            "spanNulls": false,
            "stacking": {
              "group": "A",
              "mode": "none"
            },
            "thresholdsStyle": {
              "mode": "off"
            }
          },
          "mappings": [],
          "thresholds": {
            "mode": "absolute",
            "steps": [
              {
                "color": "green",
                "value": null
              },
              {
                "color": "red",
                "value": 80
              }
            ]
          }
        },
        "overrides": []
      },
      "gridPos": {
        "h": 8,
        "w": 12,
        "x": 0,
        "y": 16
      },
      "id": 3,
      "options": {
        "legend": {
          "calcs": [],
          "displayMode": "list",
          "placement": "bottom",
          "showLegend": true
        },
        "tooltip": {
          "mode": "single",
          "sort": "none"
        }
      },
      "targets": [
        {
          "datasource": {
            "type": "loki",
            "uid": "onprem-loki-prd-1"
          },
          "editorMode": "builder",
          "expr": "sum(count(rate({containerId=\"cdc_grpc_in\"} |= `error` [$__interval])))",
          "hide": true,
          "queryType": "range",
          "refId": "A"
        },
        {
          "datasource": {
            "type": "loki",
            "uid": "onprem-loki-prd-1"
          },
          "editorMode": "code",
          "expr": "count(rate({containerId=\"cdc_grpc_in\"} |= \"error\" [1h])) by (containerId, errorType)",
          "hide": false,
          "queryType": "range",
          "refId": "B"
        }
      ],
      "thresholds": [
        {
          "colorMode": "critical",
          "op": "gt",
          "value": 50,
          "visible": true
        }
      ],
      "title": "CDC Grpc In",
      "type": "timeseries"
    },
    {
      "datasource": {
        "type": "loki",
        "uid": "onprem-loki-prd-1"
      },
      "gridPos": {
        "h": 8,
        "w": 12,
        "x": 12,
        "y": 16
      },
      "id": 4,
      "options": {
        "dedupStrategy": "none",
        "enableLogDetails": true,
        "prettifyLogMessage": false,
        "showCommonLabels": false,
        "showLabels": false,
        "showTime": false,
        "sortOrder": "Descending",
        "wrapLogMessage": false
      },
      "targets": [
        {
          "datasource": {
            "type": "loki",
            "uid": "onprem-loki-prd-1"
          },
          "editorMode": "builder",
          "expr": "{containerId=\"cdc_grpc_in\"} |= `error`",
          "key": "Q-c5a8776e-8c93-448b-aa5c-f5611a376d54-0",
          "queryType": "range",
          "refId": "A"
        }
      ],
      "title": "CDC Grpc In Logs",
      "type": "logs"
    },
    {
      "alert": {
        "alertRuleTags": {},
        "conditions": [
          {
            "evaluator": {
              "params": [
                50
              ],
              "type": "gt"
            },
            "operator": {
              "type": "and"
            },
            "query": {
              "params": [
                "B",
                "1h",
                "now"
              ]
            },
            "reducer": {
              "params": [],
              "type": "last"
            },
            "type": "query"
          }
        ],
        "executionErrorState": "alerting",
        "for": "0",
        "frequency": "1h",
        "handler": 1,
        "message": "URL:- https://grafana.csp.infoblox.com/d/fe7459e1-ac1d-4bd9-a621-1bfa3ee2cc90/cdc-log-monitoring?orgId=1&tab=alert",
        "name": "CDC Agent Logs alert",
        "noDataState": "ok",
        "notifications": [
          {
            "uid": "f20a9478-e17e-4cca-81a3-1bce008ccc8b"
          }
        ]
      },
      "datasource": {
        "type": "loki",
        "uid": "onprem-loki-prd-1"
      },
      "fieldConfig": {
        "defaults": {
          "color": {
            "mode": "palette-classic"
          },
          "custom": {
            "axisCenteredZero": false,
            "axisColorMode": "text",
            "axisLabel": "",
            "axisPlacement": "auto",
            "barAlignment": 0,
            "drawStyle": "line",
            "fillOpacity": 0,
            "gradientMode": "none",
            "hideFrom": {
              "legend": false,
              "tooltip": false,
              "viz": false
            },
            "lineInterpolation": "linear",
            "lineWidth": 1,
            "pointSize": 5,
            "scaleDistribution": {
              "type": "linear"
            },
            "showPoints": "auto",
            "spanNulls": false,
            "stacking": {
              "group": "A",
              "mode": "none"
            },
            "thresholdsStyle": {
              "mode": "off"
            }
          },
          "mappings": [],
          "thresholds": {
            "mode": "absolute",
            "steps": [
              {
                "color": "green",
                "value": null
              },
              {
                "color": "red",
                "value": 80
              }
            ]
          }
        },
        "overrides": []
      },
      "gridPos": {
        "h": 8,
        "w": 12,
        "x": 0,
        "y": 24
      },
      "id": 7,
      "options": {
        "legend": {
          "calcs": [],
          "displayMode": "list",
          "placement": "bottom",
          "showLegend": true
        },
        "tooltip": {
          "mode": "single",
          "sort": "none"
        }
      },
      "targets": [
        {
          "datasource": {
            "type": "loki",
            "uid": "onprem-loki-prd-1"
          },
          "editorMode": "builder",
          "expr": "sum(count(rate({containerId=\"cdc_agent\"} |= `error` [$__interval])))",
          "hide": true,
          "queryType": "range",
          "refId": "A"
        },
        {
          "datasource": {
            "type": "loki",
            "uid": "onprem-loki-prd-1"
          },
          "editorMode": "code",
          "expr": "count(rate({containerId=\"cdc_agent\"} |= \"error\" [1h])) by (containerId, errorType)",
          "hide": false,
          "queryType": "range",
          "refId": "B"
        }
      ],
      "thresholds": [
        {
          "colorMode": "critical",
          "op": "gt",
          "value": 50,
          "visible": true
        }
      ],
      "title": "CDC Agent",
      "type": "timeseries"
    },
    {
      "datasource": {
        "type": "loki",
        "uid": "onprem-loki-prd-1"
      },
      "gridPos": {
        "h": 8,
        "w": 12,
        "x": 12,
        "y": 24
      },
      "id": 10,
      "options": {
        "dedupStrategy": "none",
        "enableLogDetails": true,
        "prettifyLogMessage": false,
        "showCommonLabels": false,
        "showLabels": false,
        "showTime": false,
        "sortOrder": "Descending",
        "wrapLogMessage": false
      },
      "targets": [
        {
          "datasource": {
            "type": "loki",
            "uid": "onprem-loki-prd-1"
          },
          "editorMode": "builder",
          "expr": "{containerId=\"cdc_agent\"} |= `error`",
          "key": "Q-c5a8776e-8c93-448b-aa5c-f5611a376d54-0",
          "queryType": "range",
          "refId": "A"
        }
      ],
      "title": "CDC Agent Logs",
      "type": "logs"
    },
    {
      "alert": {
        "alertRuleTags": {},
        "conditions": [
          {
            "evaluator": {
              "params": [
                50
              ],
              "type": "gt"
            },
            "operator": {
              "type": "and"
            },
            "query": {
              "params": [
                "B",
                "1h",
                "now"
              ]
            },
            "reducer": {
              "params": [],
              "type": "last"
            },
            "type": "query"
          }
        ],
        "executionErrorState": "alerting",
        "for": "0",
        "frequency": "1h",
        "handler": 1,
        "message": "",
        "name": "CDC Dns In Logs alert",
        "noDataState": "ok",
        "notifications": [
          {
            "uid": "f20a9478-e17e-4cca-81a3-1bce008ccc8b"
          }
        ]
      },
      "datasource": {
        "type": "loki",
        "uid": "onprem-loki-prd-1"
      },
      "fieldConfig": {
        "defaults": {
          "color": {
            "mode": "palette-classic"
          },
          "custom": {
            "axisCenteredZero": false,
            "axisColorMode": "text",
            "axisLabel": "",
            "axisPlacement": "auto",
            "barAlignment": 0,
            "drawStyle": "line",
            "fillOpacity": 0,
            "gradientMode": "none",
            "hideFrom": {
              "legend": false,
              "tooltip": false,
              "viz": false
            },
            "lineInterpolation": "linear",
            "lineWidth": 1,
            "pointSize": 5,
            "scaleDistribution": {
              "type": "linear"
            },
            "showPoints": "auto",
            "spanNulls": false,
            "stacking": {
              "group": "A",
              "mode": "none"
            },
            "thresholdsStyle": {
              "mode": "off"
            }
          },
          "mappings": [],
          "thresholds": {
            "mode": "absolute",
            "steps": [
              {
                "color": "green",
                "value": null
              },
              {
                "color": "red",
                "value": 80
              }
            ]
          }
        },
        "overrides": []
      },
      "gridPos": {
        "h": 8,
        "w": 12,
        "x": 0,
        "y": 32
      },
      "id": 9,
      "options": {
        "legend": {
          "calcs": [],
          "displayMode": "list",
          "placement": "bottom",
          "showLegend": true
        },
        "tooltip": {
          "mode": "single",
          "sort": "none"
        }
      },
      "targets": [
        {
          "datasource": {
            "type": "loki",
            "uid": "onprem-loki-prd-1"
          },
          "editorMode": "builder",
          "expr": "sum(count(rate({containerId=\"cdc_dns_in\"} |= `error` [$__interval])))",
          "hide": true,
          "queryType": "range",
          "refId": "A"
        },
        {
          "datasource": {
            "type": "loki",
            "uid": "onprem-loki-prd-1"
          },
          "editorMode": "code",
          "expr": "count(rate({containerId=\"cdc_dns_in\"} |= \"error\" [1h])) by (containerId, errorType)",
          "hide": false,
          "queryType": "range",
          "refId": "B"
        }
      ],
      "thresholds": [
        {
          "colorMode": "critical",
          "op": "gt",
          "value": 50,
          "visible": true
        }
      ],
      "title": "CDC Dns In",
      "type": "timeseries"
    },
    {
      "datasource": {
        "type": "loki",
        "uid": "onprem-loki-prd-1"
      },
      "fieldConfig": {
        "defaults": {
          "color": {
            "mode": "thresholds"
          },
          "custom": {
            "align": "auto",
            "cellOptions": {
              "type": "auto"
            },
            "inspect": false
          },
          "mappings": [],
          "thresholds": {
            "mode": "absolute",
            "steps": [
              {
                "color": "green",
                "value": null
              },
              {
                "color": "red",
                "value": 80
              }
            ]
          }
        },
        "overrides": []
      },
      "gridPos": {
        "h": 8,
        "w": 12,
        "x": 12,
        "y": 32
      },
      "id": 14,
      "options": {
        "cellHeight": "sm",
        "footer": {
          "countRows": false,
          "fields": "",
          "reducer": [
            "sum"
          ],
          "show": false
        },
        "showHeader": true
      },
      "pluginVersion": "9.5.10",
      "targets": [
        {
          "datasource": {
            "type": "loki",
            "uid": "onprem-loki-prd-1"
          },
          "editorMode": "builder",
          "expr": "sum(count(rate({containerId=\"cdc_dns_in\"} |= `error` [$__interval])))",
          "hide": true,
          "queryType": "range",
          "refId": "A"
        },
        {
          "datasource": {
            "type": "loki",
            "uid": "onprem-loki-prd-1"
          },
          "editorMode": "code",
          "expr": "{containerId=\"cdc_dns_in\"} |= `error`",
          "hide": false,
          "queryType": "range",
          "refId": "B"
        }
      ],
      "title": "CDC Dns In Logs",
      "type": "table"
    },
    {
      "alert": {
        "alertRuleTags": {},
        "conditions": [
          {
            "evaluator": {
              "params": [
                50
              ],
              "type": "gt"
            },
            "operator": {
              "type": "and"
            },
            "query": {
              "params": [
                "B",
                "1h",
                "now"
              ]
            },
            "reducer": {
              "params": [],
              "type": "last"
            },
            "type": "query"
          }
        ],
        "executionErrorState": "alerting",
        "for": "0",
        "frequency": "1h",
        "handler": 1,
        "message": "",
        "name": "CDC Ipmeta In Logs alert",
        "noDataState": "ok",
        "notifications": [
          {
            "uid": "f20a9478-e17e-4cca-81a3-1bce008ccc8b"
          }
        ]
      },
      "datasource": {
        "type": "loki",
        "uid": "onprem-loki-prd-1"
      },
      "fieldConfig": {
        "defaults": {
          "color": {
            "mode": "palette-classic"
          },
          "custom": {
            "axisCenteredZero": false,
            "axisColorMode": "text",
            "axisLabel": "",
            "axisPlacement": "auto",
            "barAlignment": 0,
            "drawStyle": "line",
            "fillOpacity": 0,
            "gradientMode": "none",
            "hideFrom": {
              "legend": false,
              "tooltip": false,
              "viz": false
            },
            "lineInterpolation": "linear",
            "lineWidth": 1,
            "pointSize": 5,
            "scaleDistribution": {
              "type": "linear"
            },
            "showPoints": "auto",
            "spanNulls": false,
            "stacking": {
              "group": "A",
              "mode": "none"
            },
            "thresholdsStyle": {
              "mode": "off"
            }
          },
          "mappings": [],
          "thresholds": {
            "mode": "absolute",
            "steps": [
              {
                "color": "green",
                "value": null
              },
              {
                "color": "red",
                "value": 80
              }
            ]
          }
        },
        "overrides": []
      },
      "gridPos": {
        "h": 8,
        "w": 12,
        "x": 0,
        "y": 40
      },
      "id": 13,
      "options": {
        "legend": {
          "calcs": [],
          "displayMode": "list",
          "placement": "bottom",
          "showLegend": true
        },
        "tooltip": {
          "mode": "single",
          "sort": "none"
        }
      },
      "targets": [
        {
          "datasource": {
            "type": "loki",
            "uid": "onprem-loki-prd-1"
          },
          "editorMode": "builder",
          "expr": "sum(count(rate({containerId=\"cdc_ipmeta_in\"} |= `error` [$__interval])))",
          "hide": true,
          "queryType": "range",
          "refId": "A"
        },
        {
          "datasource": {
            "type": "loki",
            "uid": "onprem-loki-prd-1"
          },
          "editorMode": "code",
          "expr": "count(rate({containerId=\"cdc_ipmeta_in\"} |= \"error\" [1h])) by (containerId, errorType)",
          "hide": false,
          "queryType": "range",
          "refId": "B"
        }
      ],
      "thresholds": [
        {
          "colorMode": "critical",
          "op": "gt",
          "value": 50,
          "visible": true
        }
      ],
      "title": "CDC Ipmeta In",
      "type": "timeseries"
    },
    {
      "datasource": {
        "type": "loki",
        "uid": "onprem-loki-prd-1"
      },
      "gridPos": {
        "h": 8,
        "w": 12,
        "x": 12,
        "y": 40
      },
      "id": 11,
      "options": {
        "dedupStrategy": "none",
        "enableLogDetails": true,
        "prettifyLogMessage": false,
        "showCommonLabels": false,
        "showLabels": false,
        "showTime": false,
        "sortOrder": "Descending",
        "wrapLogMessage": false
      },
      "targets": [
        {
          "datasource": {
            "type": "loki",
            "uid": "onprem-loki-prd-1"
          },
          "editorMode": "builder",
          "expr": "{containerId=\"cdc_ipmeta_in\"} |= `error`",
          "key": "Q-c5a8776e-8c93-448b-aa5c-f5611a376d54-0",
          "queryType": "range",
          "refId": "A"
        }
      ],
      "title": "CDC Ipmeta In Logs",
      "type": "logs"
    },
    {
      "alert": {
        "alertRuleTags": {},
        "conditions": [
          {
            "evaluator": {
              "params": [
                50
              ],
              "type": "gt"
            },
            "operator": {
              "type": "and"
            },
            "query": {
              "params": [
                "B",
                "1h",
                "now"
              ]
            },
            "reducer": {
              "params": [],
              "type": "last"
            },
            "type": "query"
          }
        ],
        "executionErrorState": "alerting",
        "for": "0",
        "frequency": "1h",
        "handler": 1,
        "message": "",
        "name": "CDC Rpz In Logs alert",
        "noDataState": "ok",
        "notifications": [
          {
            "uid": "f20a9478-e17e-4cca-81a3-1bce008ccc8b"
          }
        ]
      },
      "datasource": {
        "type": "loki",
        "uid": "onprem-loki-prd-1"
      },
      "fieldConfig": {
        "defaults": {
          "color": {
            "mode": "palette-classic"
          },
          "custom": {
            "axisCenteredZero": false,
            "axisColorMode": "text",
            "axisLabel": "",
            "axisPlacement": "auto",
            "barAlignment": 0,
            "drawStyle": "line",
            "fillOpacity": 0,
            "gradientMode": "none",
            "hideFrom": {
              "legend": false,
              "tooltip": false,
              "viz": false
            },
            "lineInterpolation": "linear",
            "lineWidth": 1,
            "pointSize": 5,
            "scaleDistribution": {
              "type": "linear"
            },
            "showPoints": "auto",
            "spanNulls": false,
            "stacking": {
              "group": "A",
              "mode": "none"
            },
            "thresholdsStyle": {
              "mode": "off"
            }
          },
          "mappings": [],
          "thresholds": {
            "mode": "absolute",
            "steps": [
              {
                "color": "green",
                "value": null
              },
              {
                "color": "red",
                "value": 80
              }
            ]
          }
        },
        "overrides": []
      },
      "gridPos": {
        "h": 8,
        "w": 12,
        "x": 0,
        "y": 48
      },
      "id": 15,
      "options": {
        "legend": {
          "calcs": [],
          "displayMode": "list",
          "placement": "bottom",
          "showLegend": true
        },
        "tooltip": {
          "mode": "single",
          "sort": "none"
        }
      },
      "targets": [
        {
          "datasource": {
            "type": "loki",
            "uid": "onprem-loki-prd-1"
          },
          "editorMode": "builder",
          "expr": "sum(count(rate({containerId=\"cdc_rpz_in\"} |= `error` [$__interval])))",
          "hide": true,
          "queryType": "range",
          "refId": "A"
        },
        {
          "datasource": {
            "type": "loki",
            "uid": "onprem-loki-prd-1"
          },
          "editorMode": "code",
          "expr": "count(rate({containerId=\"cdc_rpz_in\"} |= \"error\" [1h])) by (containerId, errorType)",
          "hide": false,
          "queryType": "range",
          "refId": "B"
        }
      ],
      "thresholds": [
        {
          "colorMode": "critical",
          "op": "gt",
          "value": 50,
          "visible": true
        }
      ],
      "title": "CDC Rpz In",
      "type": "timeseries"
    },
    {
      "datasource": {
        "type": "loki",
        "uid": "onprem-loki-prd-1"
      },
      "gridPos": {
        "h": 8,
        "w": 12,
        "x": 12,
        "y": 48
      },
      "id": 16,
      "options": {
        "dedupStrategy": "none",
        "enableLogDetails": true,
        "prettifyLogMessage": false,
        "showCommonLabels": false,
        "showLabels": false,
        "showTime": false,
        "sortOrder": "Descending",
        "wrapLogMessage": false
      },
      "targets": [
        {
          "datasource": {
            "type": "loki",
            "uid": "onprem-loki-prd-1"
          },
          "editorMode": "builder",
          "expr": "{containerId=\"cdc_rpz_in\"} |= `error`",
          "key": "Q-c5a8776e-8c93-448b-aa5c-f5611a376d54-0",
          "queryType": "range",
          "refId": "A"
        }
      ],
      "title": "CDC Rpz In Logs",
      "type": "logs"
    },
    {
      "alert": {
        "alertRuleTags": {},
        "conditions": [
          {
            "evaluator": {
              "params": [
                50
              ],
              "type": "gt"
            },
            "operator": {
              "type": "and"
            },
            "query": {
              "params": [
                "B",
                "1h",
                "now"
              ]
            },
            "reducer": {
              "params": [],
              "type": "last"
            },
            "type": "query"
          }
        ],
        "executionErrorState": "alerting",
        "for": "0",
        "frequency": "1h",
        "handler": 1,
        "message": "URL:- https://grafana.csp.infoblox.com/d/fe7459e1-ac1d-4bd9-a621-1bfa3ee2cc90/cdc-log-monitoring?orgId=1&tab=alert",
        "name": "CDC Splunkcloud Logs alert",
        "noDataState": "ok",
        "notifications": [
          {
            "uid": "f20a9478-e17e-4cca-81a3-1bce008ccc8b"
          }
        ]
      },
      "datasource": {
        "type": "loki",
        "uid": "onprem-loki-prd-1"
      },
      "fieldConfig": {
        "defaults": {
          "color": {
            "mode": "palette-classic"
          },
          "custom": {
            "axisCenteredZero": false,
            "axisColorMode": "text",
            "axisLabel": "",
            "axisPlacement": "auto",
            "barAlignment": 0,
            "drawStyle": "line",
            "fillOpacity": 0,
            "gradientMode": "none",
            "hideFrom": {
              "legend": false,
              "tooltip": false,
              "viz": false
            },
            "lineInterpolation": "linear",
            "lineWidth": 1,
            "pointSize": 5,
            "scaleDistribution": {
              "type": "linear"
            },
            "showPoints": "auto",
            "spanNulls": false,
            "stacking": {
              "group": "A",
              "mode": "none"
            },
            "thresholdsStyle": {
              "mode": "off"
            }
          },
          "mappings": [],
          "thresholds": {
            "mode": "absolute",
            "steps": [
              {
                "color": "green",
                "value": null
              },
              {
                "color": "red",
                "value": 80
              }
            ]
          }
        },
        "overrides": []
      },
      "gridPos": {
        "h": 8,
        "w": 12,
        "x": 0,
        "y": 56
      },
      "id": 17,
      "options": {
        "legend": {
          "calcs": [],
          "displayMode": "list",
          "placement": "bottom",
          "showLegend": true
        },
        "tooltip": {
          "mode": "single",
          "sort": "none"
        }
      },
      "targets": [
        {
          "datasource": {
            "type": "loki",
            "uid": "onprem-loki-prd-1"
          },
          "editorMode": "builder",
          "expr": "sum(count(rate({containerId=\"cdc_splunkcloud_out\"} |= `error` [$__interval])))",
          "hide": true,
          "queryType": "range",
          "refId": "A"
        },
        {
          "datasource": {
            "type": "loki",
            "uid": "onprem-loki-prd-1"
          },
          "editorMode": "code",
          "expr": "count(rate({containerId=\"cdc_splunkcloud_out\"} |= \"error\" [1h])) by (containerId, errorType)",
          "hide": false,
          "queryType": "range",
          "refId": "B"
        }
      ],
      "thresholds": [
        {
          "colorMode": "critical",
          "op": "gt",
          "value": 50,
          "visible": true
        }
      ],
      "title": "CDC Splunkcloud",
      "type": "timeseries"
    },
    {
      "datasource": {
        "type": "loki",
        "uid": "onprem-loki-prd-1"
      },
      "gridPos": {
        "h": 8,
        "w": 12,
        "x": 12,
        "y": 56
      },
      "id": 18,
      "options": {
        "dedupStrategy": "none",
        "enableLogDetails": true,
        "prettifyLogMessage": false,
        "showCommonLabels": false,
        "showLabels": false,
        "showTime": false,
        "sortOrder": "Descending",
        "wrapLogMessage": false
      },
      "targets": [
        {
          "datasource": {
            "type": "loki",
            "uid": "onprem-loki-prd-1"
          },
          "editorMode": "builder",
          "expr": "{containerId=\"cdc_splunkcloud_out\"} |= `error`",
          "key": "Q-c5a8776e-8c93-448b-aa5c-f5611a376d54-0",
          "queryType": "range",
          "refId": "A"
        }
      ],
      "title": "CDC Splunkcloud out Logs",
      "type": "logs"
    },
    {
      "alert": {
        "alertRuleTags": {},
        "conditions": [
          {
            "evaluator": {
              "params": [
                50
              ],
              "type": "gt"
            },
            "operator": {
              "type": "and"
            },
            "query": {
              "params": [
                "B",
                "1h",
                "now"
              ]
            },
            "reducer": {
              "params": [],
              "type": "last"
            },
            "type": "query"
          }
        ],
        "executionErrorState": "alerting",
        "for": "0",
        "frequency": "1h",
        "handler": 1,
        "message": "URL:- https://grafana.csp.infoblox.com/d/fe7459e1-ac1d-4bd9-a621-1bfa3ee2cc90/cdc-log-monitoring?orgId=1&tab=alert",
        "name": "CDC Splunk Logs alert",
        "noDataState": "ok",
        "notifications": [
          {
            "uid": "f20a9478-e17e-4cca-81a3-1bce008ccc8b"
          }
        ]
      },
      "datasource": {
        "type": "loki",
        "uid": "onprem-loki-prd-1"
      },
      "fieldConfig": {
        "defaults": {
          "color": {
            "mode": "palette-classic"
          },
          "custom": {
            "axisCenteredZero": false,
            "axisColorMode": "text",
            "axisLabel": "",
            "axisPlacement": "auto",
            "barAlignment": 0,
            "drawStyle": "line",
            "fillOpacity": 0,
            "gradientMode": "none",
            "hideFrom": {
              "legend": false,
              "tooltip": false,
              "viz": false
            },
            "lineInterpolation": "linear",
            "lineWidth": 1,
            "pointSize": 5,
            "scaleDistribution": {
              "type": "linear"
            },
            "showPoints": "auto",
            "spanNulls": false,
            "stacking": {
              "group": "A",
              "mode": "none"
            },
            "thresholdsStyle": {
              "mode": "off"
            }
          },
          "mappings": [],
          "thresholds": {
            "mode": "absolute",
            "steps": [
              {
                "color": "green",
                "value": null
              },
              {
                "color": "red",
                "value": 80
              }
            ]
          }
        },
        "overrides": []
      },
      "gridPos": {
        "h": 8,
        "w": 12,
        "x": 0,
        "y": 64
      },
      "id": 19,
      "options": {
        "legend": {
          "calcs": [],
          "displayMode": "list",
          "placement": "bottom",
          "showLegend": true
        },
        "tooltip": {
          "mode": "single",
          "sort": "none"
        }
      },
      "targets": [
        {
          "datasource": {
            "type": "loki",
            "uid": "onprem-loki-prd-1"
          },
          "editorMode": "builder",
          "expr": "sum(count(rate({containerId=\"cdc_splunk_out\"} |= `error` [$__interval])))",
          "hide": true,
          "queryType": "range",
          "refId": "A"
        },
        {
          "datasource": {
            "type": "loki",
            "uid": "onprem-loki-prd-1"
          },
          "editorMode": "code",
          "expr": "count(rate({containerId=\"cdc_splunk_out\"} |= \"error\" [1h])) by (containerId, errorType)",
          "hide": false,
          "queryType": "range",
          "refId": "B"
        }
      ],
      "thresholds": [
        {
          "colorMode": "critical",
          "op": "gt",
          "value": 50,
          "visible": true
        }
      ],
      "title": "CDC Splunk",
      "type": "timeseries"
    },
    {
      "datasource": {
        "type": "loki",
        "uid": "onprem-loki-prd-1"
      },
      "gridPos": {
        "h": 8,
        "w": 12,
        "x": 12,
        "y": 64
      },
      "id": 20,
      "options": {
        "dedupStrategy": "none",
        "enableLogDetails": true,
        "prettifyLogMessage": false,
        "showCommonLabels": false,
        "showLabels": false,
        "showTime": false,
        "sortOrder": "Descending",
        "wrapLogMessage": false
      },
      "targets": [
        {
          "datasource": {
            "type": "loki",
            "uid": "onprem-loki-prd-1"
          },
          "editorMode": "builder",
          "expr": "{containerId=\"cdc_splunk_out\"} |= `error`",
          "key": "Q-c5a8776e-8c93-448b-aa5c-f5611a376d54-0",
          "queryType": "range",
          "refId": "A"
        }
      ],
      "title": "CDC Splunk out Logs",
      "type": "logs"
    },
    {
      "alert": {
        "alertRuleTags": {},
        "conditions": [
          {
            "evaluator": {
              "params": [
                50
              ],
              "type": "gt"
            },
            "operator": {
              "type": "and"
            },
            "query": {
              "params": [
                "B",
                "1h",
                "now"
              ]
            },
            "reducer": {
              "params": [],
              "type": "last"
            },
            "type": "query"
          }
        ],
        "executionErrorState": "alerting",
        "for": "0",
        "frequency": "1h",
        "handler": 1,
        "message": "",
        "name": "CDC Reporting out Logs alert",
        "noDataState": "ok",
        "notifications": [
          {
            "uid": "f20a9478-e17e-4cca-81a3-1bce008ccc8b"
          }
        ]
      },
      "datasource": {
        "type": "loki",
        "uid": "onprem-loki-prd-1"
      },
      "fieldConfig": {
        "defaults": {
          "color": {
            "mode": "palette-classic"
          },
          "custom": {
            "axisCenteredZero": false,
            "axisColorMode": "text",
            "axisLabel": "",
            "axisPlacement": "auto",
            "barAlignment": 0,
            "drawStyle": "line",
            "fillOpacity": 0,
            "gradientMode": "none",
            "hideFrom": {
              "legend": false,
              "tooltip": false,
              "viz": false
            },
            "lineInterpolation": "linear",
            "lineWidth": 1,
            "pointSize": 5,
            "scaleDistribution": {
              "type": "linear"
            },
            "showPoints": "auto",
            "spanNulls": false,
            "stacking": {
              "group": "A",
              "mode": "none"
            },
            "thresholdsStyle": {
              "mode": "off"
            }
          },
          "mappings": [],
          "thresholds": {
            "mode": "absolute",
            "steps": [
              {
                "color": "green",
                "value": null
              },
              {
                "color": "red",
                "value": 80
              }
            ]
          }
        },
        "overrides": []
      },
      "gridPos": {
        "h": 8,
        "w": 12,
        "x": 0,
        "y": 72
      },
      "id": 21,
      "options": {
        "legend": {
          "calcs": [],
          "displayMode": "list",
          "placement": "bottom",
          "showLegend": true
        },
        "tooltip": {
          "mode": "single",
          "sort": "none"
        }
      },
      "targets": [
        {
          "datasource": {
            "type": "loki",
            "uid": "onprem-loki-prd-1"
          },
          "editorMode": "builder",
          "expr": "sum(count(rate({containerId=\"cdc_reporting_out\"} |= `error` [$__interval])))",
          "hide": true,
          "queryType": "range",
          "refId": "A"
        },
        {
          "datasource": {
            "type": "loki",
            "uid": "onprem-loki-prd-1"
          },
          "editorMode": "code",
          "expr": "count(rate({containerId=\"cdc_reporting_out\"} |= \"error\" [1h])) by (containerId, errorType)",
          "hide": false,
          "queryType": "range",
          "refId": "B"
        }
      ],
      "thresholds": [
        {
          "colorMode": "critical",
          "op": "gt",
          "value": 50,
          "visible": true
        }
      ],
      "title": "CDC Reporting out",
      "type": "timeseries"
    },
    {
      "datasource": {
        "type": "loki",
        "uid": "onprem-loki-prd-1"
      },
      "gridPos": {
        "h": 8,
        "w": 12,
        "x": 12,
        "y": 72
      },
      "id": 22,
      "options": {
        "dedupStrategy": "none",
        "enableLogDetails": true,
        "prettifyLogMessage": false,
        "showCommonLabels": false,
        "showLabels": false,
        "showTime": false,
        "sortOrder": "Descending",
        "wrapLogMessage": false
      },
      "targets": [
        {
          "datasource": {
            "type": "loki",
            "uid": "onprem-loki-prd-1"
          },
          "editorMode": "builder",
          "expr": "{containerId=\"cdc_reporting_out\"} |= `error`",
          "key": "Q-c5a8776e-8c93-448b-aa5c-f5611a376d54-0",
          "queryType": "range",
          "refId": "A"
        }
      ],
      "title": "CDC Reporting out Logs",
      "type": "logs"
    },
    {
      "alert": {
        "alertRuleTags": {},
        "conditions": [
          {
            "evaluator": {
              "params": [
                50
              ],
              "type": "gt"
            },
            "operator": {
              "type": "and"
            },
            "query": {
              "params": [
                "B",
                "1h",
                "now"
              ]
            },
            "reducer": {
              "params": [],
              "type": "last"
            },
            "type": "query"
          }
        ],
        "executionErrorState": "alerting",
        "for": "0",
        "frequency": "1h",
        "handler": 1,
        "message": "",
        "name": "CDC Siem out Logs alert",
        "noDataState": "ok",
        "notifications": [
          {
            "uid": "f20a9478-e17e-4cca-81a3-1bce008ccc8b"
          }
        ]
      },
      "datasource": {
        "type": "loki",
        "uid": "onprem-loki-prd-1"
      },
      "fieldConfig": {
        "defaults": {
          "color": {
            "mode": "palette-classic"
          },
          "custom": {
            "axisCenteredZero": false,
            "axisColorMode": "text",
            "axisLabel": "",
            "axisPlacement": "auto",
            "barAlignment": 0,
            "drawStyle": "line",
            "fillOpacity": 0,
            "gradientMode": "none",
            "hideFrom": {
              "legend": false,
              "tooltip": false,
              "viz": false
            },
            "lineInterpolation": "linear",
            "lineWidth": 1,
            "pointSize": 5,
            "scaleDistribution": {
              "type": "linear"
            },
            "showPoints": "auto",
            "spanNulls": false,
            "stacking": {
              "group": "A",
              "mode": "none"
            },
            "thresholdsStyle": {
              "mode": "off"
            }
          },
          "mappings": [],
          "thresholds": {
            "mode": "absolute",
            "steps": [
              {
                "color": "green",
                "value": null
              },
              {
                "color": "red",
                "value": 80
              }
            ]
          }
        },
        "overrides": []
      },
      "gridPos": {
        "h": 8,
        "w": 12,
        "x": 0,
        "y": 80
      },
      "id": 25,
      "options": {
        "legend": {
          "calcs": [],
          "displayMode": "list",
          "placement": "bottom",
          "showLegend": true
        },
        "tooltip": {
          "mode": "single",
          "sort": "none"
        }
      },
      "targets": [
        {
          "datasource": {
            "type": "loki",
            "uid": "onprem-loki-prd-1"
          },
          "editorMode": "builder",
          "expr": "sum(count(rate({containerId=\"cdc_siem_out\"} |= `error` [$__interval])))",
          "hide": true,
          "queryType": "range",
          "refId": "A"
        },
        {
          "datasource": {
            "type": "loki",
            "uid": "onprem-loki-prd-1"
          },
          "editorMode": "code",
          "expr": "count(rate({containerId=\"cdc_siem_out\"} |= \"error\" [1h])) by (containerId, errorType)",
          "hide": false,
          "queryType": "range",
          "refId": "B"
        }
      ],
      "thresholds": [
        {
          "colorMode": "critical",
          "op": "gt",
          "value": 50,
          "visible": true
        }
      ],
      "title": "CDC Siem out",
      "type": "timeseries"
    },
    {
      "datasource": {
        "type": "loki",
        "uid": "onprem-loki-prd-1"
      },
      "gridPos": {
        "h": 8,
        "w": 12,
        "x": 12,
        "y": 80
      },
      "id": 24,
      "options": {
        "dedupStrategy": "none",
        "enableLogDetails": true,
        "prettifyLogMessage": false,
        "showCommonLabels": false,
        "showLabels": false,
        "showTime": false,
        "sortOrder": "Descending",
        "wrapLogMessage": false
      },
      "targets": [
        {
          "datasource": {
            "type": "loki",
            "uid": "onprem-loki-prd-1"
          },
          "editorMode": "builder",
          "expr": "{containerId=\"cdc_siem_out\"} |= `error`",
          "key": "Q-c5a8776e-8c93-448b-aa5c-f5611a376d54-0",
          "queryType": "range",
          "refId": "A"
        }
      ],
      "title": "CDC Siem out Logs",
      "type": "logs"
    },
    {
      "alert": {
        "alertRuleTags": {},
        "conditions": [
          {
            "evaluator": {
              "params": [
                50
              ],
              "type": "gt"
            },
            "operator": {
              "type": "and"
            },
            "query": {
              "params": [
                "B",
                "1h",
                "now"
              ]
            },
            "reducer": {
              "params": [],
              "type": "last"
            },
            "type": "query"
          }
        ],
        "executionErrorState": "alerting",
        "for": "0",
        "frequency": "1h",
        "handler": 1,
        "message": "",
        "name": "CDC Http out Logs alert",
        "noDataState": "ok",
        "notifications": [
          {
            "uid": "f20a9478-e17e-4cca-81a3-1bce008ccc8b"
          }
        ]
      },
      "datasource": {
        "type": "loki",
        "uid": "onprem-loki-prd-1"
      },
      "fieldConfig": {
        "defaults": {
          "color": {
            "mode": "palette-classic"
          },
          "custom": {
            "axisCenteredZero": false,
            "axisColorMode": "text",
            "axisLabel": "",
            "axisPlacement": "auto",
            "barAlignment": 0,
            "drawStyle": "line",
            "fillOpacity": 0,
            "gradientMode": "none",
            "hideFrom": {
              "legend": false,
              "tooltip": false,
              "viz": false
            },
            "lineInterpolation": "linear",
            "lineWidth": 1,
            "pointSize": 5,
            "scaleDistribution": {
              "type": "linear"
            },
            "showPoints": "auto",
            "spanNulls": false,
            "stacking": {
              "group": "A",
              "mode": "none"
            },
            "thresholdsStyle": {
              "mode": "off"
            }
          },
          "mappings": [],
          "thresholds": {
            "mode": "absolute",
            "steps": [
              {
                "color": "green",
                "value": null
              },
              {
                "color": "red",
                "value": 80
              }
            ]
          }
        },
        "overrides": []
      },
      "gridPos": {
        "h": 8,
        "w": 12,
        "x": 0,
        "y": 88
      },
      "id": 23,
      "options": {
        "legend": {
          "calcs": [],
          "displayMode": "list",
          "placement": "bottom",
          "showLegend": true
        },
        "tooltip": {
          "mode": "single",
          "sort": "none"
        }
      },
      "targets": [
        {
          "datasource": {
            "type": "loki",
            "uid": "onprem-loki-prd-1"
          },
          "editorMode": "builder",
          "expr": "sum(count(rate({containerId=\"cdc_http_out\"} |= `error` [$__interval])))",
          "hide": true,
          "queryType": "range",
          "refId": "A"
        },
        {
          "datasource": {
            "type": "loki",
            "uid": "onprem-loki-prd-1"
          },
          "editorMode": "code",
          "expr": "count(rate({containerId=\"cdc_http_out\"} |= \"error\" [1h])) by (containerId, errorType)",
          "hide": false,
          "queryType": "range",
          "refId": "B"
        }
      ],
      "thresholds": [
        {
          "colorMode": "critical",
          "op": "gt",
          "value": 50,
          "visible": true
        }
      ],
      "title": "CDC Http out",
      "type": "timeseries"
    },
    {
      "datasource": {
        "type": "loki",
        "uid": "onprem-loki-prd-1"
      },
      "gridPos": {
        "h": 8,
        "w": 12,
        "x": 12,
        "y": 88
      },
      "id": 31,
      "options": {
        "dedupStrategy": "none",
        "enableLogDetails": true,
        "prettifyLogMessage": false,
        "showCommonLabels": false,
        "showLabels": false,
        "showTime": false,
        "sortOrder": "Descending",
        "wrapLogMessage": false
      },
      "targets": [
        {
          "datasource": {
            "type": "loki",
            "uid": "onprem-loki-prd-1"
          },
          "editorMode": "code",
          "expr": "{containerId=\"cdc_http_out\"} |= `error`",
          "queryType": "range",
          "refId": "A"
        }
      ],
      "title": "CDC Http out Logs",
      "type": "logs"
    },
    {
      "datasource": {
        "type": "loki",
        "uid": "loki-infra-logging-prd-1-001"
      },
      "fieldConfig": {
        "defaults": {
          "color": {
            "mode": "thresholds"
          },
          "custom": {
            "align": "auto",
            "cellOptions": {
              "type": "auto"
            },
            "inspect": false
          },
          "mappings": [],
          "thresholds": {
            "mode": "absolute",
            "steps": [
              {
                "color": "green",
                "value": null
              },
              {
                "color": "red",
                "value": 80
              }
            ]
          }
        },
        "overrides": []
      },
      "gridPos": {
        "h": 8,
        "w": 12,
        "x": 0,
        "y": 96
      },
      "id": 26,
      "options": {
        "cellHeight": "sm",
        "footer": {
          "countRows": false,
          "fields": "",
          "reducer": [
            "sum"
          ],
          "show": false
        },
        "showHeader": true
      },
      "pluginVersion": "9.5.10",
      "targets": [
        {
          "datasource": {
            "type": "loki",
            "uid": "loki-infra-logging-prd-1-001"
          },
          "editorMode": "code",
          "expr": "{cluster=\"prd-1\", namespace=\"cdc-flow\"}",
          "key": "Q-c5a8776e-8c93-448b-aa5c-f5611a376d54-0",
          "queryType": "range",
          "refId": "A"
        }
      ],
      "title": "CDC flow Logs",
      "type": "table"
    },
    {
      "datasource": {
        "type": "loki",
        "uid": "loki-infra-logging-prd-1-001"
      },
      "fieldConfig": {
        "defaults": {
          "color": {
            "mode": "thresholds"
          },
          "custom": {
            "align": "auto",
            "cellOptions": {
              "type": "auto"
            },
            "inspect": false
          },
          "mappings": [],
          "thresholds": {
            "mode": "absolute",
            "steps": [
              {
                "color": "green",
                "value": null
              },
              {
                "color": "red",
                "value": 80
              }
            ]
          }
        },
        "overrides": []
      },
      "gridPos": {
        "h": 8,
        "w": 12,
        "x": 12,
        "y": 96
      },
      "id": 28,
      "options": {
        "cellHeight": "sm",
        "footer": {
          "countRows": false,
          "fields": "",
          "reducer": [
            "sum"
          ],
          "show": false
        },
        "showHeader": true
      },
      "pluginVersion": "9.5.10",
      "targets": [
        {
          "datasource": {
            "type": "loki",
            "uid": "loki-infra-logging-prd-1-001"
          },
          "editorMode": "builder",
          "expr": "{cluster=\"prd-1\", namespace=\"cdc-flow\", container=\"cdc-flow-hostapp-sync\"} |~ `error`",
          "key": "Q-c5a8776e-8c93-448b-aa5c-f5611a376d54-0",
          "queryType": "range",
          "refId": "A"
        }
      ],
      "title": "CDC flow  Hostapp sync Logs",
      "type": "table"
    },
    {
      "datasource": {
        "type": "loki",
        "uid": "loki-infra-logging-prd-1-001"
      },
      "fieldConfig": {
        "defaults": {
          "color": {
            "mode": "thresholds"
          },
          "custom": {
            "align": "auto",
            "cellOptions": {
              "type": "auto"
            },
            "inspect": false
          },
          "mappings": [],
          "thresholds": {
            "mode": "absolute",
            "steps": [
              {
                "color": "green",
                "value": null
              },
              {
                "color": "red",
                "value": 80
              }
            ]
          }
        },
        "overrides": []
      },
      "gridPos": {
        "h": 8,
        "w": 12,
        "x": 0,
        "y": 104
      },
      "id": 29,
      "options": {
        "cellHeight": "sm",
        "footer": {
          "countRows": false,
          "fields": "",
          "reducer": [
            "sum"
          ],
          "show": false
        },
        "showHeader": true
      },
      "pluginVersion": "9.5.10",
      "targets": [
        {
          "datasource": {
            "type": "loki",
            "uid": "loki-infra-logging-prd-1-001"
          },
          "editorMode": "code",
          "expr": "{cluster=\"prd-1\", namespace=\"data-exporter-kafka\", container=\"data-exporter-kafka\"} |~ `error`",
          "queryType": "range",
          "refId": "A"
        }
      ],
      "title": "Data Exporter Kafka Logs",
      "type": "table"
    },
    {
      "datasource": {
        "type": "loki",
        "uid": "loki-infra-logging-prd-1-001"
      },
      "fieldConfig": {
        "defaults": {
          "color": {
            "mode": "thresholds"
          },
          "custom": {
            "align": "auto",
            "cellOptions": {
              "type": "auto"
            },
            "inspect": false
          },
          "mappings": [],
          "thresholds": {
            "mode": "absolute",
            "steps": [
              {
                "color": "green",
                "value": null
              },
              {
                "color": "red",
                "value": 80
              }
            ]
          }
        },
        "overrides": []
      },
      "gridPos": {
        "h": 8,
        "w": 12,
        "x": 12,
        "y": 104
      },
      "id": 30,
      "options": {
        "cellHeight": "sm",
        "footer": {
          "countRows": false,
          "fields": "",
          "reducer": [
            "sum"
          ],
          "show": false
        },
        "showHeader": true
      },
      "pluginVersion": "9.5.10",
      "targets": [
        {
          "datasource": {
            "type": "loki",
            "uid": "loki-infra-logging-prd-1-001"
          },
          "editorMode": "code",
          "expr": "{cluster=\"prd-1\", namespace=\"cdc-data-flow\"} |~ `error`",
          "queryType": "range",
          "refId": "A"
        }
      ],
      "title": "cdc data flow Logs",
      "type": "table"
    },
    {
      "datasource": {
        "type": "loki",
        "uid": "loki-infra-logging-prd-1-001"
      },
      "gridPos": {
        "h": 8,
        "w": 12,
        "x": 0,
        "y": 112
      },
      "id": 32,
      "options": {
        "dedupStrategy": "none",
        "enableLogDetails": true,
        "prettifyLogMessage": false,
        "showCommonLabels": false,
        "showLabels": false,
        "showTime": false,
        "sortOrder": "Descending",
        "wrapLogMessage": false
      },
      "targets": [
        {
          "datasource": {
            "type": "loki",
            "uid": "loki-infra-logging-prd-1-001"
          },
          "editorMode": "code",
          "expr": "{cluster=\"prd-1\", namespace=\"cdc-flow\", pod=~\"cdc-status-reporter.*\" }",
          "queryType": "range",
          "refId": "A"
        }
      ],
      "title": "CDC Reporting status",
      "type": "logs"
    }
  ],
  "refresh": "",
  "schemaVersion": 38,
  "style": "dark",
  "tags": [],
  "templating": {
    "list": []
  },
  "time": {
    "from": "now-1h",
    "to": "now"
  },
  "timepicker": {},
  "timezone": "",
  "title": "CDC Log Monitoring",
  "uid": "fe7459e1-ac1d-4bd9-a621-1bfa3ee2cc90",
  "version": 222,
  "weekStart": ""
}